exlab/__init__.py
exlab/core.py
exlab/formal/__init__.py
exlab/formal/parameter.py
exlab/interface/__init__.py
exlab/interface/config.py
exlab/interface/graph.py
exlab/interface/loader.py
exlab/interface/serializer.py
exlab/interface/tracking.py
exlab/lab/__init__.py
exlab/lab/counter.py
exlab/lab/database.py
exlab/lab/experiment.py
exlab/lab/lab.py
exlab/modular/__init__.py
exlab/modular/attribute.py
exlab/modular/logger.py
exlab/modular/module.py
exlab/modular/node.py
exlab/modular/syncable.py
exlab/remote/__init__.py
exlab/remote/server.py
exlab/utils/__init__.py
exlab/utils/ensemble.py
exlab/utils/io.py
exlab/utils/path.py
exlab/utils/structure.py
exlab/utils/text.py
exlab/utils/varname.py
exlab-0.1.2.dist-info/LICENSE
exlab-0.1.2.dist-info/METADATA
exlab-0.1.2.dist-info/WHEEL
exlab-0.1.2.dist-info/top_level.txt
exlab-0.1.2.dist-info/RECORD
