Metadata-Version: 2.1
Name: exlab
Version: 0.1.2
Summary: A Experimental Laboratory suite
Home-page: https://github.com/Pikalchemist/exlab
Author: Alexandre Manoury
Author-email: alex@pika.tf
License: UNKNOWN
Platform: UNKNOWN
Classifier: Programming Language :: Python :: 3
Classifier: License :: OSI Approved :: MIT License
Classifier: Operating System :: OS Independent
License-File: LICENSE
Requires-Dist: coloredlogs
Requires-Dist: executing
Requires-Dist: Flask
Requires-Dist: Flask-Cors
Requires-Dist: matplotlib
Requires-Dist: numpy
Requires-Dist: Pillow
Requires-Dist: PyYAML
Requires-Dist: tabulate
